CHANGELOG.txt
LICENCE.TXT
MANIFEST.in
README.txt
setup.py
kevin_sort_time_finder.egg-info/PKG-INFO
kevin_sort_time_finder.egg-info/SOURCES.txt
kevin_sort_time_finder.egg-info/dependency_links.txt
kevin_sort_time_finder.egg-info/top_level.txt
sort_time/__init__.py
sort_time/bubble_sort.py
sort_time/heap_sort.py
sort_time/insertion_sort.py
sort_time/main.py
sort_time/merge_sort.py
sort_time/quick_sort.py
sort_time/radix_sort.py
sort_time/selection_sort.py