Metadata-Version: 2.1
Name: kevin-sort-time-finder
Version: 0.0.5
Summary: Sorting exeution time finder
Home-page: 
Author: Kevin Jose Minj
Author-email: 
License: MIT
Keywords: kevin-sort-time-finder
Classifier: Development Status :: 5 - Production/Stable
Classifier: Intended Audience :: Education
Classifier: Operating System :: Microsoft :: Windows :: Windows 10
Classifier: License :: OSI Approved :: MIT License
Classifier: Programming Language :: Python :: 3
License-File: LICENCE.TXT
